HISTORY.txt
LICENSE.txt
MANIFEST.in
README
requirements.txt
setup.py
dataiku_api_client.egg-info/PKG-INFO
dataiku_api_client.egg-info/SOURCES.txt
dataiku_api_client.egg-info/dependency_links.txt
dataiku_api_client.egg-info/requires.txt
dataiku_api_client.egg-info/top_level.txt
dataikuapi/__init__.py
dataikuapi/apinode_admin_client.py
dataikuapi/apinode_client.py
dataikuapi/auth.py
dataikuapi/base_client.py
dataikuapi/dssclient.py
dataikuapi/fmclient.py
dataikuapi/govern_client.py
dataikuapi/utils.py
dataikuapi/apinode_admin/__init__.py
dataikuapi/apinode_admin/auth.py
dataikuapi/apinode_admin/service.py
dataikuapi/dss/__init__.py
dataikuapi/dss/admin.py
dataikuapi/dss/agent.py
dataikuapi/dss/agent_tool.py
dataikuapi/dss/analysis.py
dataikuapi/dss/apideployer.py
dataikuapi/dss/apiservice.py
dataikuapi/dss/app.py
dataikuapi/dss/codestudio.py
dataikuapi/dss/continuousactivity.py
dataikuapi/dss/dashboard.py
dataikuapi/dss/data_collection.py
dataikuapi/dss/data_directories_footprint.py
dataikuapi/dss/data_quality.py
dataikuapi/dss/dataset.py
dataikuapi/dss/discussion.py
dataikuapi/dss/document_extractor.py
dataikuapi/dss/drift.py
dataikuapi/dss/evaluationcomparison.py
dataikuapi/dss/evaluationstore.py
dataikuapi/dss/feature_store.py
dataikuapi/dss/flow.py
dataikuapi/dss/future.py
dataikuapi/dss/insight.py
dataikuapi/dss/job.py
dataikuapi/dss/jupyternotebook.py
dataikuapi/dss/knowledgebank.py
dataikuapi/dss/labeling_task.py
dataikuapi/dss/llm.py
dataikuapi/dss/macro.py
dataikuapi/dss/managedfolder.py
dataikuapi/dss/meaning.py
dataikuapi/dss/messaging_channel.py
dataikuapi/dss/metrics.py
dataikuapi/dss/ml.py
dataikuapi/dss/mlflow.py
dataikuapi/dss/modelcomparison.py
dataikuapi/dss/modelevaluationstore.py
dataikuapi/dss/notebook.py
dataikuapi/dss/plugin.py
dataikuapi/dss/project.py
dataikuapi/dss/project_standards.py
dataikuapi/dss/projectdeployer.py
dataikuapi/dss/projectfolder.py
dataikuapi/dss/projectlibrary.py
dataikuapi/dss/recipe.py
dataikuapi/dss/retrieval_augmented_llm.py
dataikuapi/dss/savedmodel.py
dataikuapi/dss/scenario.py
dataikuapi/dss/sqlnotebook.py
dataikuapi/dss/sqlquery.py
dataikuapi/dss/statistics.py
dataikuapi/dss/streaming_endpoint.py
