Metadata-Version: 2.4
Name: dataiku-api-client
Version: 14.3.3
Summary: Python API client for Dataiku APIs
Home-page: https://www.dataiku.com
Download-URL: https://github.com/dataiku/dataiku-api-client-python/tarball/14.3.3
Author: Dataiku
Author-email: support@dataiku.com
License: Apache Software License
Classifier: Development Status :: 5 - Production/Stable
Classifier: Intended Audience :: Developers
Classifier: License :: OSI Approved :: Apache Software License
Classifier: Topic :: Software Development :: Libraries
Classifier: Programming Language :: Python
Classifier: Operating System :: OS Independent
License-File: LICENSE.txt
Requires-Dist: requests<3
Requires-Dist: python-dateutil
Dynamic: author
Dynamic: author-email
Dynamic: classifier
Dynamic: description
Dynamic: download-url
Dynamic: home-page
Dynamic: license
Dynamic: license-file
Dynamic: requires-dist
Dynamic: summary
